src/__init__.py
src/main.py
src/data_processing/__init__.py
src/data_processing/conversion.py
src/data_processing/data_parser.py
src/utils/__init__.py
src/utils/molecular_weights.py
src/visualization/__init__.py
src/visualization/gnuplot.py
src/visualization/terminal.py
openfoam_postprocess-0.1.2.dist-info/LICENSE
openfoam_postprocess-0.1.2.dist-info/METADATA
openfoam_postprocess-0.1.2.dist-info/WHEEL
openfoam_postprocess-0.1.2.dist-info/entry_points.txt
openfoam_postprocess-0.1.2.dist-info/top_level.txt
openfoam_postprocess-0.1.2.dist-info/RECORD
