Metadata-Version: 2.2
Name: openfoam-postprocess
Version: 0.1.2
Summary: OpenFOAM 數據處理與可視化工具
Home-page: https://github.com/mactonehsieh/openfoam-postprocess
Author: Mactone Hsieh
Author-email: mactonehsieh@gmail.com
Classifier: Programming Language :: Python :: 3
Classifier: License :: OSI Approved :: MIT License
Classifier: Operating System :: OS Independent
Requires-Python: >=3.6
License-File: LICENSE
Requires-Dist: pandas>=1.0.0
Requires-Dist: numpy>=1.19.0
Dynamic: author
Dynamic: author-email
Dynamic: classifier
Dynamic: description
Dynamic: description-content-type
Dynamic: home-page
Dynamic: requires-dist
Dynamic: requires-python
Dynamic: summary
